currency_rate/__init__.py
currency_rate/converter.py
currency_rate/exceptions/__init__.py
currency_rate-0.1.2.dist-info/LICENSE
currency_rate-0.1.2.dist-info/METADATA
currency_rate-0.1.2.dist-info/WHEEL
currency_rate-0.1.2.dist-info/RECORD
