Metadata-Version: 2.1
Name: currency-rate
Version: 0.1.2
Summary: 
Author: Max
Author-email: maxim.milchakov@ya.ru
Requires-Python: >=3.8,<4.0
Classifier: Programming Language :: Python :: 3
Classifier: Programming Language :: Python :: 3.8
Classifier: Programming Language :: Python :: 3.9
Classifier: Programming Language :: Python :: 3.10
Classifier: Programming Language :: Python :: 3.11
Classifier: Programming Language :: Python :: 3.12
Requires-Dist: incremental (>=22.10.0,<23.0.0)
Requires-Dist: pydantic (>=2.6.1,<3.0.0)
Requires-Dist: requests (>=2.31.0,<3.0.0)
Requires-Dist: simplejson (>=3.19.2,<4.0.0)
